[{"confidence": "0.9578", "file_id": "354", "bbox": "1460 477 1586 634"}, {"confidence": "0.9574", "file_id": "205", "bbox": "1460 478 1586 634"}, {"confidence": "0.9569", "file_id": "143", "bbox": "1724 471 1853 628"}, {"confidence": "0.9567", "file_id": "357", "bbox": "1723 471 1852 628"}, {"confidence": "0.9553", "file_id": "27", "bbox": "1727 471 1852 628"}, {"confidence": "0.9506", "file_id": "46", "bbox": "1579 470 1705 627"}, {"confidence": "0.9505", "file_id": "519", "bbox": "1510 471 1638 631"}, {"confidence": "0.9504", "file_id": "142", "bbox": "1737 466 1869 621"}, {"confidence": "0.9500", "file_id": "272", "bbox": "1580 469 1705 627"}, {"confidence": "0.9496", "file_id": "201", "bbox": "1360 477 1487 637"}, {"confidence": "0.9493", "file_id": "50", "bbox": "1684 471 1806 628"}, {"confidence": "0.9493", "file_id": "100", "bbox": "1685 471 1806 627"}, {"confidence": "0.9492", "file_id": "515", "bbox": "1372 481 1503 638"}, {"confidence": "0.9476", "file_id": "3", "bbox": "1534 469 1662 630"}, {"confidence": "0.9472", "file_id": "458", "bbox": "1580 469 1705 627"}, {"confidence": "0.9470", "file_id": "366", "bbox": "1372 480 1503 638"}, {"confidence": "0.9470", "file_id": "390", "bbox": "1511 471 1639 631"}, {"confidence": "0.9464", "file_id": "81", "bbox": "1371 480 1503 638"}, {"confidence": "0.9464", "file_id": "380", "bbox": "1511 471 1639 631"}, {"confidence": "0.9460", "file_id": "438", "bbox": "1681 468 1808 627"}, {"confidence": "0.9449", "file_id": "370", "bbox": "1690 471 1813 626"}, {"confidence": "0.9408", "file_id": "261", "bbox": "632 510 752 671"}, {"confidence": "0.9400", "file_id": "217", "bbox": "484 504 616 675"}, {"confidence": "0.9395", "file_id": "477", "bbox": "1712 468 1843 625"}, {"confidence": "0.9392", "file_id": "66", "bbox": "1361 479 1491 639"}, {"confidence": "0.9377", "file_id": "34", "bbox": "1602 477 1736 637"}, {"confidence": "0.9377", "file_id": "404", "bbox": "1361 480 1491 639"}, {"confidence": "0.9361", "file_id": "250", "bbox": "1672 475 1794 629"}, {"confidence": "0.9360", "file_id": "140", "bbox": "1361 479 1491 639"}, {"confidence": "0.9350", "file_id": "524", "bbox": "1711 468 1843 626"}, {"confidence": "0.9332", "file_id": "11", "bbox": "1229 488 1354 648"}, {"confidence": "0.9331", "file_id": "389", "bbox": "1712 468 1843 626"}, {"confidence": "0.9323", "file_id": "190", "bbox": "1229 489 1353 647"}, {"confidence": "0.9306", "file_id": "260", "bbox": "872 508 993 666"}, {"confidence": "0.9306", "file_id": "343", "bbox": "1621 469 1747 627"}, {"confidence": "0.9305", "file_id": "548", "bbox": "1019 505 1141 665"}, {"confidence": "0.9296", "file_id": "396", "bbox": "630 506 752 667"}, {"confidence": "0.9296", "file_id": "399", "bbox": "1669 472 1796 631"}, {"confidence": "0.9293", "file_id": "84", "bbox": "1229 487 1355 647"}, {"confidence": "0.9292", "file_id": "243", "bbox": "1395 478 1522 641"}, {"confidence": "0.9281", "file_id": "234", "bbox": "1624 469 1748 627"}, {"confidence": "0.9277", "file_id": "522", "bbox": "621 499 742 659"}, {"confidence": "0.9263", "file_id": "207", "bbox": "618 498 741 658"}, {"confidence": "0.9253", "file_id": "150", "bbox": "729 521 846 675"}, {"confidence": "0.9241", "file_id": "462", "bbox": "839 496 959 652"}, {"confidence": "0.9235", "file_id": "36", "bbox": "846 507 961 659"}, {"confidence": "0.9230", "file_id": "9", "bbox": "630 506 753 666"}, {"confidence": "0.9217", "file_id": "146", "bbox": "1623 467 1749 626"}, {"confidence": "0.9196", "file_id": "147", "bbox": "861 513 982 672"}, {"confidence": "0.9191", "file_id": "324", "bbox": "1699 475 1828 638"}, {"confidence": "0.9189", "file_id": "361", "bbox": "796 507 918 661"}, {"confidence": "0.9186", "file_id": "547", "bbox": "702 526 820 683"}, {"confidence": "0.9184", "file_id": "543", "bbox": "653 518 777 679"}, {"confidence": "0.9173", "file_id": "500", "bbox": "1377 485 1507 640"}, {"confidence": "0.9167", "file_id": "412", "bbox": "701 525 817 680"}, {"confidence": "0.9156", "file_id": "116", "bbox": "1563 475 1695 638"}, {"confidence": "0.9154", "file_id": "179", "bbox": "869 510 992 670"}, {"confidence": "0.9151", "file_id": "308", "bbox": "1640 475 1768 636"}, {"confidence": "0.9143", "file_id": "277", "bbox": "701 526 817 680"}, {"confidence": "0.9142", "file_id": "87", "bbox": "1564 475 1695 638"}, {"confidence": "0.9136", "file_id": "342", "bbox": "1605 467 1740 634"}, {"confidence": "0.9134", "file_id": "332", "bbox": "1563 475 1695 637"}, {"confidence": "0.9114", "file_id": "330", "bbox": "775 503 899 658"}, {"confidence": "0.9111", "file_id": "443", "bbox": "1638 474 1769 638"}, {"confidence": "0.9099", "file_id": "26", "bbox": "1348 470 1472 629"}, {"confidence": "0.9096", "file_id": "184", "bbox": "1640 476 1768 637"}, {"confidence": "0.9085", "file_id": "352", "bbox": "718 523 838 680"}, {"confidence": "0.9084", "file_id": "290", "bbox": "1331 485 1455 642"}, {"confidence": "0.9083", "file_id": "10", "bbox": "1629 474 1753 629"}, {"confidence": "0.9077", "file_id": "306", "bbox": "1347 469 1472 629"}, {"confidence": "0.9056", "file_id": "17", "bbox": "1348 470 1472 629"}, {"confidence": "0.9052", "file_id": "275", "bbox": "1326 480 1459 640"}, {"confidence": "0.9042", "file_id": "317", "bbox": "698 506 821 664"}, {"confidence": "0.9041", "file_id": "432", "bbox": "1348 470 1473 629"}, {"confidence": "0.9036", "file_id": "171", "bbox": "699 508 821 662"}, {"confidence": "0.9036", "file_id": "249", "bbox": "888 487 1010 643"}, {"confidence": "0.9032", "file_id": "91", "bbox": "1496 478 1625 639"}, {"confidence": "0.9026", "file_id": "353", "bbox": "1674 464 1810 631"}, {"confidence": "0.9018", "file_id": "203", "bbox": "850 501 977 662"}, {"confidence": "0.9010", "file_id": "4", "bbox": "901 500 1025 660"}, {"confidence": "0.9006", "file_id": "557", "bbox": "850 501 977 660"}, {"confidence": "0.8998", "file_id": "568", "bbox": "902 499 1025 658"}, {"confidence": "0.8980", "file_id": "230", "bbox": "901 500 1026 659"}, {"confidence": "0.8951", "file_id": "107", "bbox": "1567 474 1694 631"}, {"confidence": "0.8893", "file_id": "127", "bbox": "1427 480 1559 640"}, {"confidence": "0.8889", "file_id": "51", "bbox": "1694 464 1830 630"}, {"confidence": "0.8886", "file_id": "338", "bbox": "1771 465 1901 624"}, {"confidence": "0.8883", "file_id": "252", "bbox": "1347 483 1470 643"}, {"confidence": "0.8881", "file_id": "228", "bbox": "1324 473 1453 635"}, {"confidence": "0.8863", "file_id": "465", "bbox": "852 493 974 649"}, {"confidence": "0.8820", "file_id": "339", "bbox": "1350 475 1471 631"}, {"confidence": "0.8807", "file_id": "268", "bbox": "1174 489 1297 641"}, {"confidence": "0.8803", "file_id": "101", "bbox": "786 489 911 648"}, {"confidence": "0.8800", "file_id": "422", "bbox": "1329 484 1454 643"}, {"confidence": "0.8792", "file_id": "293", "bbox": "1331 479 1462 642"}, {"confidence": "0.8783", "file_id": "48", "bbox": "816 493 938 647"}, {"confidence": "0.8766", "file_id": "559", "bbox": "1174 488 1296 641"}, {"confidence": "0.8742", "file_id": "442", "bbox": "1350 475 1471 631"}, {"confidence": "0.8740", "file_id": "406", "bbox": "1403 473 1531 634"}, {"confidence": "0.8726", "file_id": "173", "bbox": "1174 489 1297 642"}, {"confidence": "0.8695", "file_id": "534", "bbox": "712 505 844 662"}, {"confidence": "0.8688", "file_id": "204", "bbox": "1147 492 1272 646"}, {"confidence": "0.8686", "file_id": "23", "bbox": "1328 484 1453 645"}, {"confidence": "0.8668", "file_id": "561", "bbox": "1349 475 1471 631"}, {"confidence": "0.8667", "file_id": "331", "bbox": "1252 487 1381 650"}, {"confidence": "0.8664", "file_id": "516", "bbox": "1146 491 1271 647"}, {"confidence": "0.8582", "file_id": "177", "bbox": "941 501 1067 660"}, {"confidence": "0.8578", "file_id": "447", "bbox": "1147 491 1272 647"}, {"confidence": "0.8570", "file_id": "80", "bbox": "1098 491 1218 644"}, {"confidence": "0.8568", "file_id": "506", "bbox": "1697 468 1832 634"}, {"confidence": "0.8563", "file_id": "539", "bbox": "1098 491 1217 645"}, {"confidence": "0.8527", "file_id": "295", "bbox": "1393 480 1527 644"}, {"confidence": "0.8473", "file_id": "334", "bbox": "1497 480 1625 637"}, {"confidence": "0.8472", "file_id": "517", "bbox": "1127 490 1256 649"}, {"confidence": "0.8440", "file_id": "8", "bbox": "947 496 1074 657"}, {"confidence": "0.8439", "file_id": "216", "bbox": "1098 491 1217 645"}, {"confidence": "0.8436", "file_id": "305", "bbox": "1127 490 1255 649"}, {"confidence": "0.8431", "file_id": "92", "bbox": "1280 512 1407 675"}, {"confidence": "0.8380", "file_id": "498", "bbox": "1040 491 1164 644"}, {"confidence": "0.8342", "file_id": "327", "bbox": "1260 486 1389 647"}, {"confidence": "0.8275", "file_id": "360", "bbox": "1127 490 1254 648"}, {"confidence": "0.8198", "file_id": "520", "bbox": "1177 493 1304 651"}, {"confidence": "0.8181", "file_id": "452", "bbox": "1793 466 1909 622"}, {"confidence": "0.8150", "file_id": "320", "bbox": "1083 493 1205 650"}, {"confidence": "0.8126", "file_id": "545", "bbox": "1774 465 1908 624"}, {"confidence": "0.8114", "file_id": "463", "bbox": "1097 495 1223 648"}, {"confidence": "0.8106", "file_id": "199", "bbox": "1246 534 1371 701"}, {"confidence": "0.8058", "file_id": "395", "bbox": "1794 467 1909 622"}, {"confidence": "0.7990", "file_id": "417", "bbox": "1795 466 1909 622"}, {"confidence": "0.7986", "file_id": "303", "bbox": "1047 497 1178 662"}, {"confidence": "0.7939", "file_id": "221", "bbox": "1213 536 1335 700"}, {"confidence": "0.7903", "file_id": "159", "bbox": "1258 486 1388 651"}, {"confidence": "0.7834", "file_id": "455", "bbox": "959 496 1083 660"}, {"confidence": "0.7830", "file_id": "152", "bbox": "1082 493 1201 648"}, {"confidence": "0.7795", "file_id": "445", "bbox": "1232 491 1357 643"}, {"confidence": "0.7674", "file_id": "556", "bbox": "954 500 1080 658"}, {"confidence": "0.7616", "file_id": "550", "bbox": "1081 491 1201 648"}, {"confidence": "0.7558", "file_id": "512", "bbox": "1209 493 1338 645"}, {"confidence": "0.7331", "file_id": "411", "bbox": "869 490 996 640"}, {"confidence": "0.7260", "file_id": "264", "bbox": "903 494 1030 649"}, {"confidence": "0.7200", "file_id": "337", "bbox": "1245 481 1376 642"}, {"confidence": "0.7148", "file_id": "97", "bbox": "1083 495 1205 650"}, {"confidence": "0.7049", "file_id": "95", "bbox": "1050 493 1173 648"}, {"confidence": "0.7035", "file_id": "328", "bbox": "1076 493 1195 648"}, {"confidence": "0.6943", "file_id": "56", "bbox": "1106 496 1231 652"}, {"confidence": "0.6867", "file_id": "369", "bbox": "1095 493 1224 648"}, {"confidence": "0.6831", "file_id": "566", "bbox": "1009 503 1134 658"}, {"confidence": "0.6706", "file_id": "148", "bbox": "991 505 1118 656"}, {"confidence": "0.6360", "file_id": "513", "bbox": "1196 485 1323 640"}, {"confidence": "0.3174", "file_id": "153", "bbox": "1200 490 1329 648"}]